{
  "l0lee": [
    {
      "username": "ا◙☬ځُــۥـ☼ـڈ◄أڵـــســمـــٱ۽►ـۉد☼ــۥــۓ☬◙ا",
      "addedFromRoom": "كوكاكولآ",
      "addedAt": "2026-06-04T09:59:32.044Z"
    },
    {
      "username": "off",
      "addedFromRoom": "كوكاكولآ",
      "addedAt": "2026-06-21T22:50:45.853Z"
    }
  ],
  "ا◙☬ځُــۥـ☼ـڈ◄أڵـــســمـــٱ۽►ـۉد☼ــۥــۓ☬◙ا": [
    {
      "username": "˺مـ⃪טּ•ٱݪـولهٓہ˛឵឵឵឵឵឵឵឵឵឵឵឵឵឵في.خـٱفقي𝂅ݪڪ.ﯙݪٱيٱت˼",
      "addedFromRoom": "قلوبنا🖤تجمعنا",
      "addedAt": "2026-06-06T06:37:06.928Z"
    }
  ],
  "جمال": [
    {
      "username": "ا◙☬ځُــۥـ☼ـڈ◄أڵـــســمـــٱ۽►ـۉد☼ــۥــۓ☬◙ا",
      "addedFromRoom": "قلوبنا🖤تجمعنا",
      "addedAt": "2026-06-06T11:45:23.625Z"
    }
  ],
  "взтнян𑁤": [
    {
      "username": "ا◙☬ځُــۥـ☼ـڈ◄أڵـــســمـــٱ۽►ـۉد☼ــۥــۓ☬◙ا",
      "addedFromRoom": "قلوبنا🖤تجمعنا",
      "addedAt": "2026-06-06T15:00:47.012Z"
    }
  ],
  "ɗơɲʆɯƛƛɲ": [
    {
      "username": "ا◙☬ځُــۥـ☼ـڈ◄أڵـــســمـــٱ۽►ـۉد☼ــۥــۓ☬◙ا",
      "addedFromRoom": "قلوبنا🖤تجمعنا",
      "addedAt": "2026-06-07T05:03:43.921Z"
    }
  ]
}